[{
 "id": "1",
 "name": "iPhone",
 "2010": "10000",
 "2011": "16000",
 "2012": "18000"
 }, {
 "id": 2,
 "name": "iPad",
 "2010": "5000",
 "2011": "18000",
 "2012": "30000"
}, {
 "id": "3",
 "name": "iPod",
 "2010": "6000",
 "2011": "9000",
 "2012": "4000"
}, {
 "id": "4",
 "name": "Macbook",
 "2010": "26000",
 "2011": "29000",
 "2012": "44000"
}, {
 "id": "5",
 "name": "iTunes",
 "2010": "2000",
 "2011": "5000",
 "2012": "9000"
}, {
 "id": "6",
 "name": "iSoftware",
 "2010": "26000",
 "2011": "29000",
 "2012": "38000"
}, {
 "id": "7",
 "name": "iPeripherals",
 "2010": "18000",
 "2011": "26000",
 "2012": "42000"
}]